interference_calculator/__init__.py
interference_calculator/display_button_icon.svg
interference_calculator/help_button_icon.svg
interference_calculator/icon.svg
interference_calculator/main.py
interference_calculator/molecule.py
interference_calculator/periodic_table.csv
interference_calculator/ui.py
interference_calculator/ui_help.py
interference_calculator/update_periodic_table.py
interference_calculator-1.0.0.dist-info/DESCRIPTION.rst
interference_calculator-1.0.0.dist-info/LICENSE.txt
interference_calculator-1.0.0.dist-info/METADATA
interference_calculator-1.0.0.dist-info/RECORD
interference_calculator-1.0.0.dist-info/WHEEL
interference_calculator-1.0.0.dist-info/entry_points.txt
interference_calculator-1.0.0.dist-info/metadata.json
interference_calculator-1.0.0.dist-info/top_level.txt
