Metadata-Version: 2.0
Name: interference-calculator
Version: 1.0.0
Summary: Calculate mass interference and standard isotopic ratios for mass spectrometry. 
Home-page: https://github.com/zanpeeters/interference_calculator
Author: Zan Peeters
Author-email: me@example.com
License: BSD 3-Clause Clear
Keywords: interference mass-spectrometry isotope element standard ratio
Platform: UNKNOWN
Classifier: License :: OSI Approved :: BSD License
Classifier: Programming Language :: Python :: 2.7
Classifier: Programming Language :: Python :: 3
Classifier: Development Status :: 4 - Beta
Classifier: Development Status :: 5 - Production/Stable
Classifier: Intended Audience :: Science/Research
Classifier: Topic :: Scientific/Engineering
Requires-Dist: matplotlib
Requires-Dist: pandas
Requires-Dist: pyparsing
Requires-Dist: PyQt5
Requires-Dist: scipy
